setup.py
CUI/__init__.py
CUI/flow/__init__.py
CUI/flow/switcher.py
CUI/view/__init__.py
CUI/view/options.py
CUI/view/order_list.py
CUI/view/printer.py
CUI/view/selector.py
CUI/view/selector_adapter.py
CUI/view/table.py
CUI/view/tools.py
CUI/view/validator.py
CommandUI.egg-info/PKG-INFO
CommandUI.egg-info/SOURCES.txt
CommandUI.egg-info/dependency_links.txt
CommandUI.egg-info/requires.txt
CommandUI.egg-info/top_level.txt