Metadata-Version: 1.0
Name: CommandUI
Version: 1.0.6
Summary: ui tools for console
Home-page: https://coding.net/u/lin3x/p/CUI/git
Author: lishion
Author-email: 544670411@qq.com
License: MIT Licence
Keywords: pip,commandline,console,UI
Platform: any
